aioytmdesktopapi/__init__.py
aioytmdesktopapi/constants.py
aioytmdesktopapi/errors.py
aioytmdesktopapi/helpers.py
aioytmdesktopapi/player.py
aioytmdesktopapi/py.typed
aioytmdesktopapi/send_command.py
aioytmdesktopapi/track.py
aioytmdesktopapi/ytmdesktop.py
aioytmdesktopapi-0.1.2.dist-info/LICENSE
aioytmdesktopapi-0.1.2.dist-info/METADATA
aioytmdesktopapi-0.1.2.dist-info/WHEEL
aioytmdesktopapi-0.1.2.dist-info/top_level.txt
aioytmdesktopapi-0.1.2.dist-info/RECORD
