Metadata-Version: 2.1
Name: aioytmdesktopapi
Version: 0.1.2
Summary: Asyncio API package for YouTube Music Desktop app (https://ytmdesktop.app/).
Home-page: https://github.com/mvdwetering/aioytmdesktopapi
Author: Michel van de Wetering
Author-email: michel.van.de.wetering+ytmdesktop@gmail.com
License: Apache License 2.0
Keywords: automation
Classifier: Development Status :: 4 - Beta
Classifier: Intended Audience :: Developers
Classifier: License :: OSI Approved :: Apache Software License
Classifier: Programming Language :: Python :: 3 :: Only
Classifier: Operating System :: OS Independent
Classifier: Topic :: Home Automation
Classifier: Topic :: Software Development :: Libraries
License-File: LICENSE
Requires-Dist: aiohttp
